darkzseo.py
darkzseo-1.3.3.dist-info/METADATA
darkzseo-1.3.3.dist-info/WHEEL
darkzseo-1.3.3.dist-info/entry_points.txt
darkzseo-1.3.3.dist-info/top_level.txt
darkzseo-1.3.3.dist-info/RECORD
