Metadata-Version: 2.4
Name: darkzseo
Version: 1.3.3
Summary: DarkzSEO - Zero-Config 2026 Search Standard Auditor (CLI + HTML)
Home-page: https://github.com/yourusername/darkzseo
Author: DarkzSEO
Classifier: Development Status :: 5 - Production/Stable
Classifier: Intended Audience :: Developers
Classifier: Topic :: Internet :: WWW/HTTP :: Site Management
Classifier: License :: OSI Approved :: MIT License
Classifier: Programming Language :: Python :: 3
Requires-Python: >=3.7
Requires-Dist: beautifulsoup4>=4.12.0
Requires-Dist: colorama>=0.4.6
Dynamic: author
Dynamic: classifier
Dynamic: description
Dynamic: description-content-type
Dynamic: home-page
Dynamic: requires-dist
Dynamic: requires-python
Dynamic: summary
